bioseq/__init__.py
bioseq/analyzer.py
bioseq/visualizer.py
bioseq_toolkit-0.1.1.dist-info/licenses/LICENSE
bioseq_toolkit-0.1.1.dist-info/METADATA
bioseq_toolkit-0.1.1.dist-info/WHEEL
bioseq_toolkit-0.1.1.dist-info/top_level.txt
bioseq_toolkit-0.1.1.dist-info/RECORD
