Metadata-Version: 2.4
Name: bioseq-toolkit
Version: 0.1.1
Summary: Enhanced Sequence Analyzer (FASTA/ORF/protein analysis)
Author: Dheeraj Babu
License: MIT
Requires-Python: >=3.10
License-File: LICENSE
Dynamic: license-file
